test/test_util.py
test/test_modified_peptide_container.py
test/test_id_parsers.py
test/__init__.py
test/test_spec_parsers.py
test/test_spectra_container.py
test/test_ascore.py
pyascore/__main__.py
pyascore/__init__.py
pyascore/config.py
pyascore/ptm_scoring.cpython-38-x86_64-linux-gnu.so
pyascore/parsing/spec_parsers.py
pyascore/parsing/__init__.py
pyascore/parsing/id_parsers.py
pyascore-1.0.1.dist-info/WHEEL
pyascore-1.0.1.dist-info/top_level.txt
pyascore-1.0.1.dist-info/LICENSE.md
pyascore-1.0.1.dist-info/entry_points.txt
pyascore-1.0.1.dist-info/RECORD
pyascore-1.0.1.dist-info/METADATA
