Metadata-Version: 2.1
Name: pyascore
Version: 1.0.1
Summary: A python module for fast post translational modification localization.
Home-page: https://github.com/AnthonyOfSeattle/pyAscore
Author: Anthony S. Barente
Author-email: valenta4@uw.edu
License: MIT
Project-URL: Documentation, https://pyascore.readthedocs.io
Project-URL: Bug Tracker, https://github.com/AnthonyOfSeattle/pyAscore/issues
Classifier: Programming Language :: Python :: 3
Classifier: License :: OSI Approved :: Apache Software License
Classifier: Operating System :: OS Independent
Classifier: Topic :: Scientific/Engineering :: Bio-Informatics
Requires-Python: >=3.6
Provides-Extra: docs
License-File: LICENSE.md
